{
  "current": {
    "temperature": 24.3,
    "feels_like": 24.1,
    "humidity": 54,
    "wind_speed": 10.8,
    "code": 2,
    "condition": "Parçalı bulutlu"
  },
  "sun": {
    "sunrise": "05:52",
    "sunset": "20:28"
  },
  "moon": {
    "phase": "Büyüyen Ay",
    "illumination": 72,
    "icon": "🌔",
    "waxing": true
  },
  "daily": [
    {
      "day": "Cum",
      "code": 3,
      "max": 26.1,
      "min": 19.9
    },
    {
      "day": "Cmt",
      "code": 80,
      "max": 22.1,
      "min": 20.1
    },
    {
      "day": "Paz",
      "code": 3,
      "max": 25.6,
      "min": 20.0
    },
    {
      "day": "Pzt",
      "code": 1,
      "max": 29.5,
      "min": 20.6
    },
    {
      "day": "Sal",
      "code": 2,
      "max": 29.7,
      "min": 24.3
    }
  ]
}